README.md
setup.py
oh_my_logging.egg-info/PKG-INFO
oh_my_logging.egg-info/SOURCES.txt
oh_my_logging.egg-info/dependency_links.txt
oh_my_logging.egg-info/entry_points.txt
oh_my_logging.egg-info/requires.txt
oh_my_logging.egg-info/top_level.txt
src/oh_my_logging/__init__.py
src/oh_my_logging/builders/__init__.py
src/oh_my_logging/builders/function_logger_builder.py
src/oh_my_logging/builders/logger_builder.py
src/oh_my_logging/builders/logger_builder_factory.py
src/oh_my_logging/builders/str_logger_builder.py
src/oh_my_logging/builders/type_logger_builder.py
src/oh_my_logging/decorators/__init__.py
src/oh_my_logging/decorators/log.py
src/oh_my_logging/decorators/log_args.py
src/oh_my_logging/decorators/log_error.py
src/oh_my_logging/decorators/log_returning.py
src/oh_my_logging/decorators/log_stat.py
src/oh_my_logging/decorators/logger.py
src/oh_my_logging/handlers/__init__.py
src/oh_my_logging/handlers/memory_handler.py