Metadata-Version: 2.1
Name: oh-my-logging
Version: 0.1.1
Summary: Enhancement for logging.
Home-page: https://github.com/fsjohnhuang/oh-my-logging
Author: fsjohnhuang
Author-email: fsjohnhuang@hotmail.com
Maintainer: fsjohnhuang
Maintainer-email: fsjohnhuang@hotmail.com
License: MIT
Platform: any
Classifier: Development Status :: 3 - Alpha
Classifier: Operating System :: OS Independent
Classifier: Intended Audience :: Developers
Classifier: License :: OSI Approved :: MIT License
Classifier: Programming Language :: Python
Classifier: Programming Language :: Python :: Implementation
Classifier: Programming Language :: Python :: 2.7
Classifier: Programming Language :: Python :: 3
Classifier: Programming Language :: Python :: 3.1
Classifier: Programming Language :: Python :: 3.2
Classifier: Programming Language :: Python :: 3.3
Classifier: Programming Language :: Python :: 3.4
Classifier: Programming Language :: Python :: 3.5
Classifier: Programming Language :: Python :: 3.6
Classifier: Topic :: Software Development :: Libraries
Requires-Python: >=2.7
